src/aap/__init__.py
src/aap/__version__.py
src/aap/_base.py
src/aap/_group.py
src/aap/_host.py
src/aap/_inventory.py
src/aap/_organization.py
src/aap/_team.py
src/aap/_workflow.py
src/aap/adapter.py
src/aap/cnd_aap.py
cnd_aap-0.1.0.dist-info/METADATA
cnd_aap-0.1.0.dist-info/WHEEL
cnd_aap-0.1.0.dist-info/RECORD
