Metadata-Version: 2.1
Name: cnd_aap
Version: 0.1.0
Summary: Ansible Python lib for Aria Automation
Author: Denis Fabien <denis@changendevops.com>
Classifier: License :: OSI Approved :: MIT License
Classifier: Operating System :: OS Independent
Classifier: Programming Language :: Python :: 3
Requires-Python: >=3.9
Requires-Dist: cndprint
Requires-Dist: pyyaml
Requires-Dist: requests
